nomad_camels_driver_derived_channels/derived_channels.py
nomad_camels_driver_derived_channels/derived_channels_ophyd.py
nomad_camels_driver_derived_channels/multi_derived_signal.py
nomad_camels_driver_derived_channels-0.1.3.dist-info/licenses/LICENSE
nomad_camels_driver_derived_channels-0.1.3.dist-info/METADATA
nomad_camels_driver_derived_channels-0.1.3.dist-info/WHEEL
nomad_camels_driver_derived_channels-0.1.3.dist-info/top_level.txt
nomad_camels_driver_derived_channels-0.1.3.dist-info/RECORD
