Metadata-Version: 2.4
Name: nomad_camels_driver_derived_channels
Version: 0.1.3
Summary: Instrument driver for derived_channels for NOMAD CAMELS
Author-email: enter your name here! <contact@email.com>
Project-URL: NOMAD Camels GitHub, https://github.com/FAU-LAP/NOMAD-CAMELS
Project-URL: CAMELS Drivers GitHub, https://github.com/FAU-LAP/CAMELS_drivers
Project-URL: NOMAD Camels Documentation, https://fau-lap.github.io/NOMAD-CAMELS/doc/instruments/instruments.html
Classifier: Programming Language :: Python :: 3
Classifier: License :: OSI Approved :: GNU Lesser General Public License v2 (LGPLv2)
Requires-Python: >=3.9
License-File: LICENSE
Requires-Dist: nomad-camels
Requires-Dist: asyncua
Dynamic: license-file
